<?xml version="1.0" encoding="UTF-8" standalone="yes"?>
<!DOCTYPE project>
<epcismd:EPCISMasterDataDocument
	xmlns:epcismd="urn:epcglobal:epcis-masterdata:xsd:1" xmlns:xsi="http://www.w3.org/2001/XMLSchema-instance"
	schemaVersion="1.0" creationDate="2005-07-11T11:30:47.0Z">
	<EPCISBody>
		<VocabularyList>
			<Vocabulary type="urn:epcglobal:epcis:vtype:EPCInstance">
				<VocabularyElementList>
					<VocabularyElement id="urn:epc:id:sgtin:0000001.000001.1">
						<attribute id="urn:epc:cbv:mda:netWeight">3.5^double</attribute>
					</VocabularyElement>
					<VocabularyElement id="urn:epc:id:sgtin:0000001.000001.2">
						<attribute id="urn:epc:cbv:mda:netWeight">2.5^double</attribute>
					</VocabularyElement>
					<VocabularyElement id="urn:epc:id:sgtin:0000001.000001.3">
						<attribute id="urn:epc:cbv:mda:netWeight">3.1^double</attribute>
					</VocabularyElement>
					<VocabularyElement id="urn:epc:id:sgtin:0000001.000001.4">
						<attribute id="urn:epc:cbv:mda:netWeight">3.2^double</attribute>
					</VocabularyElement>
					<VocabularyElement id="urn:epc:id:sgtin:0000001.000001.5">
						<attribute id="urn:epc:cbv:mda:netWeight">5.3^double</attribute>
					</VocabularyElement>
					<VocabularyElement id="urn:epc:id:sgtin:0000001.000001.6">
						<attribute id="urn:epc:cbv:mda:netWeight">2.8^double</attribute>
					</VocabularyElement>
					<VocabularyElement id="urn:epc:id:sgtin:0000001.000001.7">
						<attribute id="urn:epc:cbv:mda:netWeight">7.1^double</attribute>
					</VocabularyElement>
					<VocabularyElement id="urn:epc:id:sgtin:0000001.000001.8">
						<attribute id="urn:epc:cbv:mda:netWeight">0.5^double</attribute>
					</VocabularyElement>
					<VocabularyElement id="urn:epc:id:sgtin:0000001.000001.9">
						<attribute id="urn:epc:cbv:mda:netWeight">8.8^double</attribute>
					</VocabularyElement>
					<VocabularyElement id="urn:epc:id:sgtin:0000001.000001.10">
						<attribute id="urn:epc:cbv:mda:netWeight">2.5^double</attribute>
					</VocabularyElement>
					<VocabularyElement id="urn:epc:id:sgtin:0000001.000002.1">
						<attribute id="urn:epc:cbv:mda:netWeight">3.5^double</attribute>
					</VocabularyElement>
					<VocabularyElement id="urn:epc:id:sgtin:0000001.000002.2">
						<attribute id="urn:epc:cbv:mda:netWeight">2.5^double</attribute>
					</VocabularyElement>
					<VocabularyElement id="urn:epc:id:sgtin:0000001.000002.3">
						<attribute id="urn:epc:cbv:mda:netWeight">3.1^double</attribute>
					</VocabularyElement>
					<VocabularyElement id="urn:epc:id:sgtin:0000001.000002.4">
						<attribute id="urn:epc:cbv:mda:netWeight">3.2^double</attribute>
					</VocabularyElement>
				</VocabularyElementList>
			</Vocabulary>
			<Vocabulary type="urn:epcglobal:epcis:vtype:BusinessLocation">
				<VocabularyElementList>
					<!-- TNT Liverpool Depot -->
					<VocabularyElement id="urn:epc:id:sgln:0000001.00001.0">
						<attribute id="urn:oliot:ubv:mda:gps">-2.844552, 53.336734^geoPoint</attribute>
					</VocabularyElement>
					<!-- TNT Leeds Depot -->
					<VocabularyElement id="urn:epc:id:sgln:0000001.00001.1">
						<attribute id="urn:oliot:ubv:mda:gps">-1.627516, 53.752503^geoPoint</attribute>
					</VocabularyElement>
					<!-- TNT Rotherham Depot -->
					<VocabularyElement id="urn:epc:id:sgln:0000001.00001.2">
						<attribute id="urn:oliot:ubv:mda:gps">-1.246341, 53.427623^geoPoint</attribute>
					</VocabularyElement>
					<!-- TNT Nottingham Depot -->
					<VocabularyElement id="urn:epc:id:sgln:0000001.00001.3">
						<attribute id="urn:oliot:ubv:mda:gps">-1.167388, 52.936254^geoPoint</attribute>
					</VocabularyElement>
					<!-- Depot near Leeds -->
					<VocabularyElement id="urn:epc:id:sgln:0000001.00002.1">
						<attribute id="urn:oliot:ubv:mda:gps">-1.627516, 53.762503^geoPoint</attribute>
					</VocabularyElement>
					<!-- Depot near Rotherham -->
					<VocabularyElement id="urn:epc:id:sgln:0000001.00002.2">
						<attribute id="urn:oliot:ubv:mda:gps">-1.246341, 53.437623^geoPoint</attribute>
					</VocabularyElement>
				</VocabularyElementList>
			</Vocabulary>
		</VocabularyList>
	</EPCISBody>
</epcismd:EPCISMasterDataDocument>